setup.py
xiaozhu/__init__.py
xiaozhu.egg-info/PKG-INFO
xiaozhu.egg-info/SOURCES.txt
xiaozhu.egg-info/dependency_links.txt
xiaozhu.egg-info/top_level.txt