Metadata-Version: 2.1
Name: xiaozhu
Version: 0.0.1
Summary: 一些实用的方法
Home-page: https://gitee.com/cxyzy1
Author: python编程小猪
Author-email: 309032663@qq.com
License: UNKNOWN
Platform: UNKNOWN
Classifier: Programming Language :: Python :: 3
Classifier: License :: OSI Approved :: MIT License
Classifier: Operating System :: OS Independent
Requires-Python: >=3.7
